{
  "timeframe": "daily",
  "horizon": 5,
  "min_bars": 260,
  "stride": 1,
  "min_conviction": 0.0,
  "bull_tau": 0.35,
  "bear_tau": -0.6,
  "per_symbol": [
    {
      "symbol": "AMZN",
      "timeframe": "daily",
      "source": "tradier",
      "bars_tested": 237,
      "total_bars": 502,
      "horizon": 5,
      "buckets": {
        "BULLISH": {
          "n": 104,
          "hit_rate": 44.23,
          "avg_return_pct": -1.27,
          "median_return_pct": -0.487,
          "stdev_pct": 3.676,
          "profit_factor": 0.38,
          "best_pct": 4.605,
          "worst_pct": -14.093
        },
        "BEARISH": {
          "n": 16,
          "hit_rate": 56.25,
          "avg_return_pct": -0.02,
          "median_return_pct": 0.453,
          "stdev_pct": 2.633,
          "profit_factor": 0.98,
          "best_pct": 4.373,
          "worst_pct": -6.747
        },
        "NEUTRAL": {
          "n": 117,
          "hit_rate": 69.23,
          "avg_return_pct": 2.258,
          "median_return_pct": 2.396,
          "stdev_pct": 4.656,
          "profit_factor": 3.66,
          "best_pct": 16.49,
          "worst_pct": -13.268
        }
      },
      "option_proxy": {
        "n": 237,
        "hit_rate": 54.85,
        "avg_return_pct": 0.333,
        "median_return_pct": 0.558,
        "stdev_pct": 7.255,
        "profit_factor": 1.13,
        "best_pct": 24.385,
        "worst_pct": -23.039
      }
    },
    {
      "symbol": "TSLA",
      "timeframe": "daily",
      "source": "tradier",
      "bars_tested": 237,
      "total_bars": 502,
      "horizon": 5,
      "buckets": {
        "BULLISH": {
          "n": 80,
          "hit_rate": 42.5,
          "avg_return_pct": -0.196,
          "median_return_pct": -0.967,
          "stdev_pct": 6.313,
          "profit_factor": 0.92,
          "best_pct": 22.447,
          "worst_pct": -11.678
        },
        "BEARISH": {
          "n": 11,
          "hit_rate": 27.27,
          "avg_return_pct": -2.801,
          "median_return_pct": -3.55,
          "stdev_pct": 4.92,
          "profit_factor": 0.26,
          "best_pct": 4.14,
          "worst_pct": -12.522
        },
        "NEUTRAL": {
          "n": 146,
          "hit_rate": 52.05,
          "avg_return_pct": 1.205,
          "median_return_pct": 0.275,
          "stdev_pct": 5.358,
          "profit_factor": 1.74,
          "best_pct": 14.807,
          "worst_pct": -9.348
        }
      },
      "option_proxy": {
        "n": 237,
        "hit_rate": 46.41,
        "avg_return_pct": 0.462,
        "median_return_pct": -1.328,
        "stdev_pct": 9.637,
        "profit_factor": 1.13,
        "best_pct": 41.402,
        "worst_pct": -23.391
      }
    },
    {
      "symbol": "META",
      "timeframe": "daily",
      "source": "tradier",
      "bars_tested": 237,
      "total_bars": 502,
      "horizon": 5,
      "buckets": {
        "BULLISH": {
          "n": 72,
          "hit_rate": 59.72,
          "avg_return_pct": 0.576,
          "median_return_pct": 0.353,
          "stdev_pct": 3.291,
          "profit_factor": 1.6,
          "best_pct": 11.044,
          "worst_pct": -5.502
        },
        "BEARISH": {
          "n": 14,
          "hit_rate": 64.29,
          "avg_return_pct": 2.635,
          "median_return_pct": 3.322,
          "stdev_pct": 4.415,
          "profit_factor": 4.62,
          "best_pct": 11.444,
          "worst_pct": -2.779
        },
        "NEUTRAL": {
          "n": 151,
          "hit_rate": 46.36,
          "avg_return_pct": -0.265,
          "median_return_pct": -0.154,
          "stdev_pct": 5.415,
          "profit_factor": 0.88,
          "best_pct": 15.206,
          "worst_pct": -16.518
        }
      },
      "option_proxy": {
        "n": 237,
        "hit_rate": 46.84,
        "avg_return_pct": 0.054,
        "median_return_pct": -0.292,
        "stdev_pct": 7.825,
        "profit_factor": 1.02,
        "best_pct": 24.131,
        "worst_pct": -25.126
      }
    },
    {
      "symbol": "NVDA",
      "timeframe": "daily",
      "source": "tradier",
      "bars_tested": 237,
      "total_bars": 502,
      "horizon": 5,
      "buckets": {
        "BULLISH": {
          "n": 116,
          "hit_rate": 56.9,
          "avg_return_pct": 0.83,
          "median_return_pct": 0.528,
          "stdev_pct": 4.981,
          "profit_factor": 1.54,
          "best_pct": 14.844,
          "worst_pct": -10.716
        },
        "BEARISH": {
          "n": 0
        },
        "NEUTRAL": {
          "n": 121,
          "hit_rate": 61.98,
          "avg_return_pct": 1.317,
          "median_return_pct": 0.995,
          "stdev_pct": 3.936,
          "profit_factor": 2.33,
          "best_pct": 10.337,
          "worst_pct": -6.987
        }
      },
      "option_proxy": {
        "n": 237,
        "hit_rate": 55.7,
        "avg_return_pct": 1.364,
        "median_return_pct": 0.906,
        "stdev_pct": 7.42,
        "profit_factor": 1.61,
        "best_pct": 25.329,
        "worst_pct": -17.603
      }
    },
    {
      "symbol": "AVGO",
      "timeframe": "daily",
      "source": "yfinance",
      "bars_tested": 236,
      "total_bars": 501,
      "horizon": 5,
      "buckets": {
        "BULLISH": {
          "n": 152,
          "hit_rate": 55.92,
          "avg_return_pct": 0.756,
          "median_return_pct": 0.753,
          "stdev_pct": 5.797,
          "profit_factor": 1.44,
          "best_pct": 22.216,
          "worst_pct": -21.055
        },
        "BEARISH": {
          "n": 10,
          "hit_rate": 10.0,
          "avg_return_pct": -6.826,
          "median_return_pct": -8.009,
          "stdev_pct": 5.092,
          "profit_factor": 0.04,
          "best_pct": 2.963,
          "worst_pct": -13.286
        },
        "NEUTRAL": {
          "n": 74,
          "hit_rate": 54.05,
          "avg_return_pct": 1.748,
          "median_return_pct": 0.582,
          "stdev_pct": 6.52,
          "profit_factor": 2.05,
          "best_pct": 20.774,
          "worst_pct": -9.023
        }
      },
      "option_proxy": {
        "n": 236,
        "hit_rate": 52.12,
        "avg_return_pct": 0.885,
        "median_return_pct": 0.577,
        "stdev_pct": 10.933,
        "profit_factor": 1.25,
        "best_pct": 41.417,
        "worst_pct": -40.144
      }
    },
    {
      "symbol": "AMD",
      "timeframe": "daily",
      "source": "yfinance",
      "bars_tested": 236,
      "total_bars": 501,
      "horizon": 5,
      "buckets": {
        "BULLISH": {
          "n": 111,
          "hit_rate": 63.06,
          "avg_return_pct": 3.185,
          "median_return_pct": 2.065,
          "stdev_pct": 9.003,
          "profit_factor": 2.54,
          "best_pct": 34.33,
          "worst_pct": -17.434
        },
        "BEARISH": {
          "n": 3,
          "hit_rate": 0.0,
          "avg_return_pct": -12.821,
          "median_return_pct": -13.002,
          "stdev_pct": 1.131,
          "profit_factor": 0.0,
          "best_pct": -11.354,
          "worst_pct": -14.106
        },
        "NEUTRAL": {
          "n": 122,
          "hit_rate": 63.11,
          "avg_return_pct": 2.925,
          "median_return_pct": 1.286,
          "stdev_pct": 9.847,
          "profit_factor": 2.5,
          "best_pct": 43.625,
          "worst_pct": -23.666
        }
      },
      "option_proxy": {
        "n": 236,
        "hit_rate": 59.32,
        "avg_return_pct": 4.134,
        "median_return_pct": 1.8,
        "stdev_pct": 15.602,
        "profit_factor": 2.11,
        "best_pct": 65.088,
        "worst_pct": -35.848
      }
    },
    {
      "symbol": "TSM",
      "timeframe": "daily",
      "source": "tradier",
      "bars_tested": 237,
      "total_bars": 502,
      "horizon": 5,
      "buckets": {
        "BULLISH": {
          "n": 169,
          "hit_rate": 58.58,
          "avg_return_pct": 1.081,
          "median_return_pct": 0.663,
          "stdev_pct": 4.0,
          "profit_factor": 2.0,
          "best_pct": 14.843,
          "worst_pct": -9.528
        },
        "BEARISH": {
          "n": 0
        },
        "NEUTRAL": {
          "n": 68,
          "hit_rate": 69.12,
          "avg_return_pct": 2.583,
          "median_return_pct": 2.652,
          "stdev_pct": 4.736,
          "profit_factor": 3.69,
          "best_pct": 12.555,
          "worst_pct": -10.468
        }
      },
      "option_proxy": {
        "n": 237,
        "hit_rate": 59.07,
        "avg_return_pct": 2.109,
        "median_return_pct": 1.84,
        "stdev_pct": 7.177,
        "profit_factor": 2.08,
        "best_pct": 23.844,
        "worst_pct": -16.452
      }
    },
    {
      "symbol": "QCOM",
      "timeframe": "daily",
      "source": "tradier",
      "bars_tested": 237,
      "total_bars": 502,
      "horizon": 5,
      "buckets": {
        "BULLISH": {
          "n": 91,
          "hit_rate": 50.55,
          "avg_return_pct": -0.565,
          "median_return_pct": 0.068,
          "stdev_pct": 5.046,
          "profit_factor": 0.75,
          "best_pct": 12.737,
          "worst_pct": -14.268
        },
        "BEARISH": {
          "n": 23,
          "hit_rate": 69.57,
          "avg_return_pct": 1.621,
          "median_return_pct": 2.121,
          "stdev_pct": 2.86,
          "profit_factor": 3.98,
          "best_pct": 6.314,
          "worst_pct": -4.382
        },
        "NEUTRAL": {
          "n": 123,
          "hit_rate": 53.66,
          "avg_return_pct": 2.226,
          "median_return_pct": 0.356,
          "stdev_pct": 7.488,
          "profit_factor": 2.79,
          "best_pct": 41.068,
          "worst_pct": -10.459
        }
      },
      "option_proxy": {
        "n": 237,
        "hit_rate": 51.48,
        "avg_return_pct": 1.353,
        "median_return_pct": 0.743,
        "stdev_pct": 10.477,
        "profit_factor": 1.48,
        "best_pct": 61.252,
        "worst_pct": -23.435
      }
    },
    {
      "symbol": "INTC",
      "timeframe": "daily",
      "source": "tradier",
      "bars_tested": 237,
      "total_bars": 502,
      "horizon": 5,
      "buckets": {
        "BULLISH": {
          "n": 151,
          "hit_rate": 58.28,
          "avg_return_pct": 4.329,
          "median_return_pct": 1.513,
          "stdev_pct": 11.097,
          "profit_factor": 3.06,
          "best_pct": 45.166,
          "worst_pct": -16.432
        },
        "BEARISH": {
          "n": 0
        },
        "NEUTRAL": {
          "n": 86,
          "hit_rate": 63.95,
          "avg_return_pct": 3.832,
          "median_return_pct": 2.838,
          "stdev_pct": 9.271,
          "profit_factor": 3.45,
          "best_pct": 35.143,
          "worst_pct": -12.506
        }
      },
      "option_proxy": {
        "n": 237,
        "hit_rate": 59.49,
        "avg_return_pct": 6.528,
        "median_return_pct": 2.817,
        "stdev_pct": 17.552,
        "profit_factor": 2.95,
        "best_pct": 80.949,
        "worst_pct": -28.614
      }
    },
    {
      "symbol": "MU",
      "timeframe": "daily",
      "source": "tradier",
      "bars_tested": 237,
      "total_bars": 502,
      "horizon": 5,
      "buckets": {
        "BULLISH": {
          "n": 181,
          "hit_rate": 66.3,
          "avg_return_pct": 4.247,
          "median_return_pct": 4.245,
          "stdev_pct": 10.073,
          "profit_factor": 2.95,
          "best_pct": 37.97,
          "worst_pct": -19.99
        },
        "BEARISH": {
          "n": 0
        },
        "NEUTRAL": {
          "n": 56,
          "hit_rate": 75.0,
          "avg_return_pct": 5.49,
          "median_return_pct": 5.459,
          "stdev_pct": 8.993,
          "profit_factor": 4.68,
          "best_pct": 27.12,
          "worst_pct": -20.415
        }
      },
      "option_proxy": {
        "n": 237,
        "hit_rate": 68.35,
        "avg_return_pct": 7.313,
        "median_return_pct": 7.561,
        "stdev_pct": 17.122,
        "profit_factor": 2.99,
        "best_pct": 62.681,
        "worst_pct": -37.931
      }
    },
    {
      "symbol": "AMAT",
      "timeframe": "daily",
      "source": "tradier",
      "bars_tested": 237,
      "total_bars": 502,
      "horizon": 5,
      "buckets": {
        "BULLISH": {
          "n": 175,
          "hit_rate": 61.71,
          "avg_return_pct": 1.38,
          "median_return_pct": 1.593,
          "stdev_pct": 5.865,
          "profit_factor": 1.83,
          "best_pct": 14.906,
          "worst_pct": -15.298
        },
        "BEARISH": {
          "n": 0
        },
        "NEUTRAL": {
          "n": 62,
          "hit_rate": 75.81,
          "avg_return_pct": 4.411,
          "median_return_pct": 4.402,
          "stdev_pct": 6.384,
          "profit_factor": 5.86,
          "best_pct": 17.311,
          "worst_pct": -15.087
        }
      },
      "option_proxy": {
        "n": 237,
        "hit_rate": 64.14,
        "avg_return_pct": 3.328,
        "median_return_pct": 3.131,
        "stdev_pct": 10.589,
        "profit_factor": 2.24,
        "best_pct": 27.982,
        "worst_pct": -24.673
      }
    },
    {
      "symbol": "ASML",
      "timeframe": "daily",
      "source": "tradier",
      "bars_tested": 237,
      "total_bars": 502,
      "horizon": 5,
      "buckets": {
        "BULLISH": {
          "n": 154,
          "hit_rate": 55.84,
          "avg_return_pct": 1.022,
          "median_return_pct": 0.488,
          "stdev_pct": 5.495,
          "profit_factor": 1.62,
          "best_pct": 16.529,
          "worst_pct": -14.282
        },
        "BEARISH": {
          "n": 0
        },
        "NEUTRAL": {
          "n": 83,
          "hit_rate": 66.27,
          "avg_return_pct": 2.714,
          "median_return_pct": 2.344,
          "stdev_pct": 5.501,
          "profit_factor": 3.65,
          "best_pct": 16.216,
          "worst_pct": -8.445
        }
      },
      "option_proxy": {
        "n": 237,
        "hit_rate": 58.23,
        "avg_return_pct": 2.141,
        "median_return_pct": 1.409,
        "stdev_pct": 9.402,
        "profit_factor": 1.81,
        "best_pct": 30.393,
        "worst_pct": -29.627
      }
    },
    {
      "symbol": "MRVL",
      "timeframe": "daily",
      "source": "tradier",
      "bars_tested": 237,
      "total_bars": 502,
      "horizon": 5,
      "buckets": {
        "BULLISH": {
          "n": 112,
          "hit_rate": 54.46,
          "avg_return_pct": 1.691,
          "median_return_pct": 0.984,
          "stdev_pct": 8.403,
          "profit_factor": 1.68,
          "best_pct": 24.564,
          "worst_pct": -17.998
        },
        "BEARISH": {
          "n": 7,
          "hit_rate": 42.86,
          "avg_return_pct": -5.335,
          "median_return_pct": -8.565,
          "stdev_pct": 7.193,
          "profit_factor": 0.17,
          "best_pct": 3.728,
          "worst_pct": -15.843
        },
        "NEUTRAL": {
          "n": 118,
          "hit_rate": 66.95,
          "avg_return_pct": 2.819,
          "median_return_pct": 2.8,
          "stdev_pct": 7.049,
          "profit_factor": 2.89,
          "best_pct": 24.136,
          "worst_pct": -16.092
        }
      },
      "option_proxy": {
        "n": 237,
        "hit_rate": 59.92,
        "avg_return_pct": 2.938,
        "median_return_pct": 2.629,
        "stdev_pct": 13.074,
        "profit_factor": 1.8,
        "best_pct": 39.444,
        "worst_pct": -32.387
      }
    },
    {
      "symbol": "SNDK",
      "timeframe": "daily",
      "source": "tradier",
      "bars_tested": 53,
      "total_bars": 318,
      "horizon": 5,
      "buckets": {
        "BULLISH": {
          "n": 50,
          "hit_rate": 72.0,
          "avg_return_pct": 9.078,
          "median_return_pct": 9.41,
          "stdev_pct": 14.698,
          "profit_factor": 4.39,
          "best_pct": 40.302,
          "worst_pct": -21.878
        },
        "BEARISH": {
          "n": 0
        },
        "NEUTRAL": {
          "n": 3,
          "hit_rate": 66.67,
          "avg_return_pct": 11.914,
          "median_return_pct": 16.317,
          "stdev_pct": 12.198,
          "profit_factor": 8.55,
          "best_pct": 24.157,
          "worst_pct": -4.733
        }
      },
      "option_proxy": {
        "n": 53,
        "hit_rate": 71.7,
        "avg_return_pct": 16.186,
        "median_return_pct": 16.023,
        "stdev_pct": 26.544,
        "profit_factor": 4.34,
        "best_pct": 72.194,
        "worst_pct": -44.325
      }
    },
    {
      "symbol": "AAPL",
      "timeframe": "daily",
      "source": "tradier",
      "bars_tested": 237,
      "total_bars": 502,
      "horizon": 5,
      "buckets": {
        "BULLISH": {
          "n": 119,
          "hit_rate": 61.34,
          "avg_return_pct": 0.829,
          "median_return_pct": 0.888,
          "stdev_pct": 3.047,
          "profit_factor": 1.98,
          "best_pct": 9.416,
          "worst_pct": -5.377
        },
        "BEARISH": {
          "n": 5,
          "hit_rate": 0.0,
          "avg_return_pct": -2.572,
          "median_return_pct": -2.571,
          "stdev_pct": 1.018,
          "profit_factor": 0.0,
          "best_pct": -0.947,
          "worst_pct": -4.066
        },
        "NEUTRAL": {
          "n": 113,
          "hit_rate": 53.1,
          "avg_return_pct": 0.877,
          "median_return_pct": 0.307,
          "stdev_pct": 3.829,
          "profit_factor": 1.82,
          "best_pct": 13.326,
          "worst_pct": -8.033
        }
      },
      "option_proxy": {
        "n": 237,
        "hit_rate": 52.32,
        "avg_return_pct": 0.955,
        "median_return_pct": 0.862,
        "stdev_pct": 5.623,
        "profit_factor": 1.54,
        "best_pct": 19.64,
        "worst_pct": -12.399
      }
    },
    {
      "symbol": "PANW",
      "timeframe": "daily",
      "source": "tradier",
      "bars_tested": 237,
      "total_bars": 502,
      "horizon": 5,
      "buckets": {
        "BULLISH": {
          "n": 66,
          "hit_rate": 53.03,
          "avg_return_pct": -0.118,
          "median_return_pct": 0.306,
          "stdev_pct": 6.179,
          "profit_factor": 0.94,
          "best_pct": 24.015,
          "worst_pct": -16.381
        },
        "BEARISH": {
          "n": 21,
          "hit_rate": 76.19,
          "avg_return_pct": 4.757,
          "median_return_pct": 4.777,
          "stdev_pct": 5.564,
          "profit_factor": 8.74,
          "best_pct": 13.663,
          "worst_pct": -5.195
        },
        "NEUTRAL": {
          "n": 150,
          "hit_rate": 66.0,
          "avg_return_pct": 1.703,
          "median_return_pct": 2.244,
          "stdev_pct": 5.398,
          "profit_factor": 2.25,
          "best_pct": 21.208,
          "worst_pct": -12.768
        }
      },
      "option_proxy": {
        "n": 237,
        "hit_rate": 61.6,
        "avg_return_pct": 1.997,
        "median_return_pct": 2.361,
        "stdev_pct": 9.543,
        "profit_factor": 1.75,
        "best_pct": 37.113,
        "worst_pct": -26.888
      }
    },
    {
      "symbol": "SPY",
      "timeframe": "daily",
      "source": "tradier",
      "bars_tested": 237,
      "total_bars": 502,
      "horizon": 5,
      "buckets": {
        "BULLISH": {
          "n": 142,
          "hit_rate": 62.68,
          "avg_return_pct": 0.266,
          "median_return_pct": 0.386,
          "stdev_pct": 1.268,
          "profit_factor": 1.68,
          "best_pct": 2.965,
          "worst_pct": -3.356
        },
        "BEARISH": {
          "n": 0
        },
        "NEUTRAL": {
          "n": 95,
          "hit_rate": 65.26,
          "avg_return_pct": 0.758,
          "median_return_pct": 0.693,
          "stdev_pct": 1.941,
          "profit_factor": 2.61,
          "best_pct": 5.346,
          "worst_pct": -3.572
        }
      },
      "option_proxy": {
        "n": 237,
        "hit_rate": 59.92,
        "avg_return_pct": 0.371,
        "median_return_pct": 0.458,
        "stdev_pct": 2.579,
        "profit_factor": 1.44,
        "best_pct": 7.669,
        "worst_pct": -6.39
      }
    },
    {
      "symbol": "QQQ",
      "timeframe": "daily",
      "source": "tradier",
      "bars_tested": 237,
      "total_bars": 502,
      "horizon": 5,
      "buckets": {
        "BULLISH": {
          "n": 137,
          "hit_rate": 62.77,
          "avg_return_pct": 0.489,
          "median_return_pct": 0.688,
          "stdev_pct": 2.012,
          "profit_factor": 1.86,
          "best_pct": 6.006,
          "worst_pct": -5.148
        },
        "BEARISH": {
          "n": 0
        },
        "NEUTRAL": {
          "n": 100,
          "hit_rate": 61.0,
          "avg_return_pct": 0.855,
          "median_return_pct": 0.994,
          "stdev_pct": 2.444,
          "profit_factor": 2.4,
          "best_pct": 6.798,
          "worst_pct": -5.054
        }
      },
      "option_proxy": {
        "n": 237,
        "hit_rate": 59.07,
        "avg_return_pct": 0.683,
        "median_return_pct": 0.924,
        "stdev_pct": 3.591,
        "profit_factor": 1.61,
        "best_pct": 9.846,
        "worst_pct": -8.637
      }
    },
    {
      "symbol": "NFLX",
      "timeframe": "daily",
      "source": "tradier",
      "bars_tested": 237,
      "total_bars": 502,
      "horizon": 5,
      "buckets": {
        "BULLISH": {
          "n": 46,
          "hit_rate": 54.35,
          "avg_return_pct": 0.749,
          "median_return_pct": 0.476,
          "stdev_pct": 4.472,
          "profit_factor": 1.5,
          "best_pct": 8.371,
          "worst_pct": -11.185
        },
        "BEARISH": {
          "n": 21,
          "hit_rate": 71.43,
          "avg_return_pct": 0.936,
          "median_return_pct": 1.682,
          "stdev_pct": 3.905,
          "profit_factor": 1.81,
          "best_pct": 6.59,
          "worst_pct": -9.857
        },
        "NEUTRAL": {
          "n": 170,
          "hit_rate": 35.29,
          "avg_return_pct": -0.876,
          "median_return_pct": -1.286,
          "stdev_pct": 5.632,
          "profit_factor": 0.62,
          "best_pct": 27.716,
          "worst_pct": -13.888
        }
      },
      "option_proxy": {
        "n": 237,
        "hit_rate": 40.93,
        "avg_return_pct": -0.903,
        "median_return_pct": -1.634,
        "stdev_pct": 8.644,
        "profit_factor": 0.74,
        "best_pct": 43.442,
        "worst_pct": -21.321
      }
    },
    {
      "symbol": "GOOGL",
      "timeframe": "daily",
      "source": "tradier",
      "bars_tested": 237,
      "total_bars": 502,
      "horizon": 5,
      "buckets": {
        "BULLISH": {
          "n": 168,
          "hit_rate": 64.88,
          "avg_return_pct": 1.741,
          "median_return_pct": 1.26,
          "stdev_pct": 3.99,
          "profit_factor": 3.27,
          "best_pct": 13.775,
          "worst_pct": -7.336
        },
        "BEARISH": {
          "n": 1,
          "hit_rate": 100.0,
          "avg_return_pct": 0.992,
          "median_return_pct": 0.992,
          "stdev_pct": 0.0,
          "profit_factor": null,
          "best_pct": 0.992,
          "worst_pct": 0.992
        },
        "NEUTRAL": {
          "n": 68,
          "hit_rate": 67.65,
          "avg_return_pct": 2.16,
          "median_return_pct": 1.667,
          "stdev_pct": 5.354,
          "profit_factor": 2.82,
          "best_pct": 13.745,
          "worst_pct": -9.455
        }
      },
      "option_proxy": {
        "n": 237,
        "hit_rate": 64.14,
        "avg_return_pct": 2.862,
        "median_return_pct": 1.9,
        "stdev_pct": 7.479,
        "profit_factor": 2.8,
        "best_pct": 23.066,
        "worst_pct": -15.384
      }
    },
    {
      "symbol": "MSFT",
      "timeframe": "daily",
      "source": "tradier",
      "bars_tested": 237,
      "total_bars": 502,
      "horizon": 5,
      "buckets": {
        "BULLISH": {
          "n": 68,
          "hit_rate": 57.35,
          "avg_return_pct": 0.25,
          "median_return_pct": 0.28,
          "stdev_pct": 2.094,
          "profit_factor": 1.35,
          "best_pct": 4.515,
          "worst_pct": -5.117
        },
        "BEARISH": {
          "n": 27,
          "hit_rate": 77.78,
          "avg_return_pct": 2.537,
          "median_return_pct": 3.195,
          "stdev_pct": 3.555,
          "profit_factor": 5.81,
          "best_pct": 9.188,
          "worst_pct": -8.448
        },
        "NEUTRAL": {
          "n": 142,
          "hit_rate": 58.45,
          "avg_return_pct": 0.066,
          "median_return_pct": 0.443,
          "stdev_pct": 3.848,
          "profit_factor": 1.05,
          "best_pct": 14.0,
          "worst_pct": -14.435
        }
      },
      "option_proxy": {
        "n": 237,
        "hit_rate": 55.7,
        "avg_return_pct": 0.443,
        "median_return_pct": 0.45,
        "stdev_pct": 5.834,
        "profit_factor": 1.24,
        "best_pct": 23.449,
        "worst_pct": -22.002
      }
    },
    {
      "symbol": "ORCL",
      "timeframe": "daily",
      "source": "tradier",
      "bars_tested": 237,
      "total_bars": 502,
      "horizon": 5,
      "buckets": {
        "BULLISH": {
          "n": 85,
          "hit_rate": 48.24,
          "avg_return_pct": -0.37,
          "median_return_pct": -0.175,
          "stdev_pct": 5.932,
          "profit_factor": 0.84,
          "best_pct": 26.972,
          "worst_pct": -13.832
        },
        "BEARISH": {
          "n": 38,
          "hit_rate": 63.16,
          "avg_return_pct": 1.618,
          "median_return_pct": 3.146,
          "stdev_pct": 10.329,
          "profit_factor": 1.53,
          "best_pct": 19.247,
          "worst_pct": -29.363
        },
        "NEUTRAL": {
          "n": 114,
          "hit_rate": 52.63,
          "avg_return_pct": 2.011,
          "median_return_pct": 0.947,
          "stdev_pct": 10.496,
          "profit_factor": 1.72,
          "best_pct": 46.937,
          "worst_pct": -19.977
        }
      },
      "option_proxy": {
        "n": 237,
        "hit_rate": 51.9,
        "avg_return_pct": 1.345,
        "median_return_pct": 0.635,
        "stdev_pct": 15.147,
        "profit_factor": 1.28,
        "best_pct": 70.055,
        "worst_pct": -58.489
      }
    },
    {
      "symbol": "CRM",
      "timeframe": "daily",
      "source": "tradier",
      "bars_tested": 237,
      "total_bars": 502,
      "horizon": 5,
      "buckets": {
        "BULLISH": {
          "n": 10,
          "hit_rate": 20.0,
          "avg_return_pct": -4.573,
          "median_return_pct": -3.799,
          "stdev_pct": 4.154,
          "profit_factor": 0.02,
          "best_pct": 0.562,
          "worst_pct": -12.63
        },
        "BEARISH": {
          "n": 52,
          "hit_rate": 44.23,
          "avg_return_pct": -0.175,
          "median_return_pct": -0.737,
          "stdev_pct": 4.964,
          "profit_factor": 0.92,
          "best_pct": 10.068,
          "worst_pct": -10.415
        },
        "NEUTRAL": {
          "n": 175,
          "hit_rate": 49.14,
          "avg_return_pct": -0.835,
          "median_return_pct": -0.146,
          "stdev_pct": 4.773,
          "profit_factor": 0.63,
          "best_pct": 13.026,
          "worst_pct": -15.162
        }
      },
      "option_proxy": {
        "n": 237,
        "hit_rate": 43.88,
        "avg_return_pct": -1.658,
        "median_return_pct": -1.351,
        "stdev_pct": 8.132,
        "profit_factor": 0.58,
        "best_pct": 22.055,
        "worst_pct": -24.969
      }
    },
    {
      "symbol": "PLTR",
      "timeframe": "daily",
      "source": "tradier",
      "bars_tested": 237,
      "total_bars": 502,
      "horizon": 5,
      "buckets": {
        "BULLISH": {
          "n": 102,
          "hit_rate": 58.82,
          "avg_return_pct": 0.776,
          "median_return_pct": 1.347,
          "stdev_pct": 6.962,
          "profit_factor": 1.33,
          "best_pct": 21.19,
          "worst_pct": -15.628
        },
        "BEARISH": {
          "n": 15,
          "hit_rate": 40.0,
          "avg_return_pct": -1.415,
          "median_return_pct": -0.685,
          "stdev_pct": 4.439,
          "profit_factor": 0.36,
          "best_pct": 3.733,
          "worst_pct": -14.556
        },
        "NEUTRAL": {
          "n": 120,
          "hit_rate": 45.0,
          "avg_return_pct": -0.187,
          "median_return_pct": -0.563,
          "stdev_pct": 6.584,
          "profit_factor": 0.93,
          "best_pct": 14.314,
          "worst_pct": -14.48
        }
      },
      "option_proxy": {
        "n": 237,
        "hit_rate": 48.52,
        "avg_return_pct": -0.04,
        "median_return_pct": -0.168,
        "stdev_pct": 10.988,
        "profit_factor": 0.99,
        "best_pct": 35.038,
        "worst_pct": -27.279
      }
    },
    {
      "symbol": "HOOD",
      "timeframe": "daily",
      "source": "tradier",
      "bars_tested": 237,
      "total_bars": 502,
      "horizon": 5,
      "buckets": {
        "BULLISH": {
          "n": 113,
          "hit_rate": 57.52,
          "avg_return_pct": 1.947,
          "median_return_pct": 1.439,
          "stdev_pct": 7.463,
          "profit_factor": 1.94,
          "best_pct": 22.633,
          "worst_pct": -14.653
        },
        "BEARISH": {
          "n": 26,
          "hit_rate": 53.85,
          "avg_return_pct": -0.027,
          "median_return_pct": 1.006,
          "stdev_pct": 7.659,
          "profit_factor": 0.99,
          "best_pct": 10.692,
          "worst_pct": -31.161
        },
        "NEUTRAL": {
          "n": 98,
          "hit_rate": 43.88,
          "avg_return_pct": -1.067,
          "median_return_pct": -2.263,
          "stdev_pct": 10.096,
          "profit_factor": 0.76,
          "best_pct": 27.355,
          "worst_pct": -28.21
        }
      },
      "option_proxy": {
        "n": 237,
        "hit_rate": 50.63,
        "avg_return_pct": 0.625,
        "median_return_pct": 0.584,
        "stdev_pct": 14.645,
        "profit_factor": 1.12,
        "best_pct": 46.7,
        "worst_pct": -58.62
      }
    },
    {
      "symbol": "GME",
      "timeframe": "daily",
      "source": "tradier",
      "bars_tested": 237,
      "total_bars": 502,
      "horizon": 5,
      "buckets": {
        "BULLISH": {
          "n": 48,
          "hit_rate": 37.5,
          "avg_return_pct": -4.494,
          "median_return_pct": -3.324,
          "stdev_pct": 7.925,
          "profit_factor": 0.17,
          "best_pct": 7.717,
          "worst_pct": -25.152
        },
        "BEARISH": {
          "n": 28,
          "hit_rate": 35.71,
          "avg_return_pct": -1.76,
          "median_return_pct": -0.971,
          "stdev_pct": 4.028,
          "profit_factor": 0.26,
          "best_pct": 5.272,
          "worst_pct": -14.739
        },
        "NEUTRAL": {
          "n": 161,
          "hit_rate": 49.69,
          "avg_return_pct": 0.349,
          "median_return_pct": -0.049,
          "stdev_pct": 4.859,
          "profit_factor": 1.2,
          "best_pct": 13.791,
          "worst_pct": -9.846
        }
      },
      "option_proxy": {
        "n": 237,
        "hit_rate": 45.57,
        "avg_return_pct": -1.915,
        "median_return_pct": -1.423,
        "stdev_pct": 9.743,
        "profit_factor": 0.57,
        "best_pct": 23.509,
        "worst_pct": -44.115
      }
    },
    {
      "symbol": "BABA",
      "timeframe": "daily",
      "source": "tradier",
      "bars_tested": 237,
      "total_bars": 502,
      "horizon": 5,
      "buckets": {
        "BULLISH": {
          "n": 61,
          "hit_rate": 57.38,
          "avg_return_pct": 1.323,
          "median_return_pct": 2.326,
          "stdev_pct": 7.388,
          "profit_factor": 1.53,
          "best_pct": 18.729,
          "worst_pct": -15.434
        },
        "BEARISH": {
          "n": 11,
          "hit_rate": 36.36,
          "avg_return_pct": -0.457,
          "median_return_pct": -0.388,
          "stdev_pct": 2.867,
          "profit_factor": 0.64,
          "best_pct": 4.971,
          "worst_pct": -6.352
        },
        "NEUTRAL": {
          "n": 165,
          "hit_rate": 49.09,
          "avg_return_pct": 0.071,
          "median_return_pct": -0.112,
          "stdev_pct": 5.154,
          "profit_factor": 1.04,
          "best_pct": 15.775,
          "worst_pct": -12.484
        }
      },
      "option_proxy": {
        "n": 237,
        "hit_rate": 49.37,
        "avg_return_pct": 0.397,
        "median_return_pct": -0.222,
        "stdev_pct": 9.587,
        "profit_factor": 1.11,
        "best_pct": 34.861,
        "worst_pct": -25.044
      }
    },
    {
      "symbol": "JPM",
      "timeframe": "daily",
      "source": "tradier",
      "bars_tested": 237,
      "total_bars": 502,
      "horizon": 5,
      "buckets": {
        "BULLISH": {
          "n": 117,
          "hit_rate": 59.83,
          "avg_return_pct": 0.224,
          "median_return_pct": 0.599,
          "stdev_pct": 2.581,
          "profit_factor": 1.24,
          "best_pct": 5.399,
          "worst_pct": -7.086
        },
        "BEARISH": {
          "n": 5,
          "hit_rate": 0.0,
          "avg_return_pct": -4.948,
          "median_return_pct": -4.803,
          "stdev_pct": 0.433,
          "profit_factor": 0.0,
          "best_pct": -4.458,
          "worst_pct": -5.722
        },
        "NEUTRAL": {
          "n": 115,
          "hit_rate": 51.3,
          "avg_return_pct": 0.154,
          "median_return_pct": 0.102,
          "stdev_pct": 2.711,
          "profit_factor": 1.15,
          "best_pct": 6.17,
          "worst_pct": -5.349
        }
      },
      "option_proxy": {
        "n": 237,
        "hit_rate": 52.74,
        "avg_return_pct": -0.199,
        "median_return_pct": 0.391,
        "stdev_pct": 4.567,
        "profit_factor": 0.9,
        "best_pct": 10.139,
        "worst_pct": -13.742
      }
    },
    {
      "symbol": "COIN",
      "timeframe": "daily",
      "source": "tradier",
      "bars_tested": 237,
      "total_bars": 502,
      "horizon": 5,
      "buckets": {
        "BULLISH": {
          "n": 55,
          "hit_rate": 50.91,
          "avg_return_pct": 1.654,
          "median_return_pct": 1.038,
          "stdev_pct": 12.538,
          "profit_factor": 1.41,
          "best_pct": 39.992,
          "worst_pct": -19.774
        },
        "BEARISH": {
          "n": 22,
          "hit_rate": 68.18,
          "avg_return_pct": 4.825,
          "median_return_pct": 6.848,
          "stdev_pct": 7.783,
          "profit_factor": 4.24,
          "best_pct": 19.486,
          "worst_pct": -8.601
        },
        "NEUTRAL": {
          "n": 160,
          "hit_rate": 46.25,
          "avg_return_pct": 0.021,
          "median_return_pct": -0.782,
          "stdev_pct": 8.889,
          "profit_factor": 1.01,
          "best_pct": 27.932,
          "worst_pct": -26.639
        }
      },
      "option_proxy": {
        "n": 237,
        "hit_rate": 49.37,
        "avg_return_pct": 1.171,
        "median_return_pct": -0.573,
        "stdev_pct": 16.394,
        "profit_factor": 1.21,
        "best_pct": 64.837,
        "worst_pct": -47.235
      }
    },
    {
      "symbol": "XOM",
      "timeframe": "daily",
      "source": "tradier",
      "bars_tested": 237,
      "total_bars": 502,
      "horizon": 5,
      "buckets": {
        "BULLISH": {
          "n": 138,
          "hit_rate": 55.07,
          "avg_return_pct": 0.51,
          "median_return_pct": 0.522,
          "stdev_pct": 3.335,
          "profit_factor": 1.46,
          "best_pct": 9.883,
          "worst_pct": -8.95
        },
        "BEARISH": {
          "n": 0
        },
        "NEUTRAL": {
          "n": 99,
          "hit_rate": 66.67,
          "avg_return_pct": 1.533,
          "median_return_pct": 2.205,
          "stdev_pct": 3.361,
          "profit_factor": 2.95,
          "best_pct": 9.256,
          "worst_pct": -5.355
        }
      },
      "option_proxy": {
        "n": 237,
        "hit_rate": 59.92,
        "avg_return_pct": 1.168,
        "median_return_pct": 1.962,
        "stdev_pct": 5.615,
        "profit_factor": 1.66,
        "best_pct": 15.858,
        "worst_pct": -16.55
      }
    },
    {
      "symbol": "BYDDY",
      "timeframe": "daily",
      "source": "tradier",
      "bars_tested": 237,
      "total_bars": 502,
      "horizon": 5,
      "buckets": {
        "BULLISH": {
          "n": 27,
          "hit_rate": 25.93,
          "avg_return_pct": -2.044,
          "median_return_pct": -1.662,
          "stdev_pct": 4.411,
          "profit_factor": 0.29,
          "best_pct": 9.375,
          "worst_pct": -10.638
        },
        "BEARISH": {
          "n": 45,
          "hit_rate": 46.67,
          "avg_return_pct": -0.864,
          "median_return_pct": -1.307,
          "stdev_pct": 3.251,
          "profit_factor": 0.55,
          "best_pct": 4.405,
          "worst_pct": -5.801
        },
        "NEUTRAL": {
          "n": 165,
          "hit_rate": 44.85,
          "avg_return_pct": -0.854,
          "median_return_pct": -0.4,
          "stdev_pct": 4.903,
          "profit_factor": 0.64,
          "best_pct": 12.156,
          "worst_pct": -13.601
        }
      },
      "option_proxy": {
        "n": 237,
        "hit_rate": 42.19,
        "avg_return_pct": -2.023,
        "median_return_pct": -1.237,
        "stdev_pct": 7.485,
        "profit_factor": 0.5,
        "best_pct": 20.923,
        "worst_pct": -21.704
      }
    },
    {
      "symbol": "QUBT",
      "timeframe": "daily",
      "source": "tradier",
      "bars_tested": 237,
      "total_bars": 502,
      "horizon": 5,
      "buckets": {
        "BULLISH": {
          "n": 56,
          "hit_rate": 41.07,
          "avg_return_pct": -0.47,
          "median_return_pct": -4.648,
          "stdev_pct": 17.531,
          "profit_factor": 0.93,
          "best_pct": 48.014,
          "worst_pct": -29.958
        },
        "BEARISH": {
          "n": 32,
          "hit_rate": 59.38,
          "avg_return_pct": 0.758,
          "median_return_pct": 1.864,
          "stdev_pct": 10.922,
          "profit_factor": 1.21,
          "best_pct": 19.11,
          "worst_pct": -39.233
        },
        "NEUTRAL": {
          "n": 149,
          "hit_rate": 45.64,
          "avg_return_pct": 0.741,
          "median_return_pct": -0.989,
          "stdev_pct": 12.194,
          "profit_factor": 1.17,
          "best_pct": 36.802,
          "worst_pct": -23.726
        }
      },
      "option_proxy": {
        "n": 237,
        "hit_rate": 46.41,
        "avg_return_pct": 0.491,
        "median_return_pct": -2.299,
        "stdev_pct": 23.285,
        "profit_factor": 1.06,
        "best_pct": 97.045,
        "worst_pct": -70.969
      }
    },
    {
      "symbol": "QBTS",
      "timeframe": "daily",
      "source": "tradier",
      "bars_tested": 237,
      "total_bars": 502,
      "horizon": 5,
      "buckets": {
        "BULLISH": {
          "n": 88,
          "hit_rate": 39.77,
          "avg_return_pct": -1.132,
          "median_return_pct": -3.052,
          "stdev_pct": 16.524,
          "profit_factor": 0.83,
          "best_pct": 51.351,
          "worst_pct": -39.058
        },
        "BEARISH": {
          "n": 11,
          "hit_rate": 72.73,
          "avg_return_pct": 4.999,
          "median_return_pct": 8.815,
          "stdev_pct": 11.179,
          "profit_factor": 2.96,
          "best_pct": 20.417,
          "worst_pct": -23.508
        },
        "NEUTRAL": {
          "n": 138,
          "hit_rate": 51.45,
          "avg_return_pct": 3.547,
          "median_return_pct": 0.522,
          "stdev_pct": 15.436,
          "profit_factor": 1.93,
          "best_pct": 55.155,
          "worst_pct": -25.883
        }
      },
      "option_proxy": {
        "n": 237,
        "hit_rate": 48.1,
        "avg_return_pct": 2.592,
        "median_return_pct": -0.598,
        "stdev_pct": 26.426,
        "profit_factor": 1.31,
        "best_pct": 97.826,
        "worst_pct": -66.357
      }
    },
    {
      "symbol": "SMR",
      "timeframe": "daily",
      "source": "tradier",
      "bars_tested": 237,
      "total_bars": 502,
      "horizon": 5,
      "buckets": {
        "BULLISH": {
          "n": 51,
          "hit_rate": 50.98,
          "avg_return_pct": 1.591,
          "median_return_pct": 1.765,
          "stdev_pct": 15.501,
          "profit_factor": 1.29,
          "best_pct": 34.072,
          "worst_pct": -32.382
        },
        "BEARISH": {
          "n": 34,
          "hit_rate": 44.12,
          "avg_return_pct": -5.112,
          "median_return_pct": -1.169,
          "stdev_pct": 16.354,
          "profit_factor": 0.43,
          "best_pct": 12.903,
          "worst_pct": -38.814
        },
        "NEUTRAL": {
          "n": 152,
          "hit_rate": 34.87,
          "avg_return_pct": -3.793,
          "median_return_pct": -4.062,
          "stdev_pct": 12.321,
          "profit_factor": 0.46,
          "best_pct": 39.869,
          "worst_pct": -35.018
        }
      },
      "option_proxy": {
        "n": 237,
        "hit_rate": 39.66,
        "avg_return_pct": -4.854,
        "median_return_pct": -4.814,
        "stdev_pct": 23.733,
        "profit_factor": 0.59,
        "best_pct": 67.112,
        "worst_pct": -76.172
      }
    },
    {
      "symbol": "OKLO",
      "timeframe": "daily",
      "source": "tradier",
      "bars_tested": 237,
      "total_bars": 502,
      "horizon": 5,
      "buckets": {
        "BULLISH": {
          "n": 105,
          "hit_rate": 54.29,
          "avg_return_pct": 3.043,
          "median_return_pct": 1.231,
          "stdev_pct": 16.738,
          "profit_factor": 1.58,
          "best_pct": 63.499,
          "worst_pct": -29.984
        },
        "BEARISH": {
          "n": 32,
          "hit_rate": 84.38,
          "avg_return_pct": 4.595,
          "median_return_pct": 3.659,
          "stdev_pct": 4.747,
          "profit_factor": 18.7,
          "best_pct": 18.983,
          "worst_pct": -2.52
        },
        "NEUTRAL": {
          "n": 100,
          "hit_rate": 43.0,
          "avg_return_pct": 1.895,
          "median_return_pct": -2.3,
          "stdev_pct": 16.073,
          "profit_factor": 1.35,
          "best_pct": 48.857,
          "worst_pct": -27.778
        }
      },
      "option_proxy": {
        "n": 237,
        "hit_rate": 53.16,
        "avg_return_pct": 4.719,
        "median_return_pct": 1.988,
        "stdev_pct": 26.002,
        "profit_factor": 1.61,
        "best_pct": 104.423,
        "worst_pct": -50.123
      }
    },
    {
      "symbol": "VIX",
      "timeframe": "daily",
      "source": "tradier",
      "bars_tested": 237,
      "total_bars": 502,
      "horizon": 5,
      "buckets": {
        "BULLISH": {
          "n": 51,
          "hit_rate": 43.14,
          "avg_return_pct": -2.51,
          "median_return_pct": -4.204,
          "stdev_pct": 16.772,
          "profit_factor": 0.7,
          "best_pct": 42.882,
          "worst_pct": -38.115
        },
        "BEARISH": {
          "n": 42,
          "hit_rate": 28.57,
          "avg_return_pct": -4.76,
          "median_return_pct": -5.45,
          "stdev_pct": 9.902,
          "profit_factor": 0.28,
          "best_pct": 13.596,
          "worst_pct": -36.504
        },
        "NEUTRAL": {
          "n": 144,
          "hit_rate": 49.31,
          "avg_return_pct": 1.052,
          "median_return_pct": -0.359,
          "stdev_pct": 12.826,
          "profit_factor": 1.27,
          "best_pct": 54.047,
          "worst_pct": -31.648
        }
      },
      "option_proxy": {
        "n": 237,
        "hit_rate": 43.04,
        "avg_return_pct": -2.019,
        "median_return_pct": -2.489,
        "stdev_pct": 22.354,
        "profit_factor": 0.78,
        "best_pct": 80.721,
        "worst_pct": -73.722
      }
    }
  ],
  "aggregate": {
    "BULLISH": {
      "n": 3571,
      "hit_rate": 56.26,
      "avg_return_pct": 1.109,
      "median_return_pct": 0.635,
      "stdev_pct": 8.269,
      "profit_factor": 1.51,
      "best_pct": 63.499,
      "worst_pct": -39.058
    },
    "BEARISH": {
      "n": 552,
      "hit_rate": 52.9,
      "avg_return_pct": -0.097,
      "median_return_pct": 0.453,
      "stdev_pct": 8.21,
      "profit_factor": 0.97,
      "best_pct": 20.417,
      "worst_pct": -39.233
    },
    "NEUTRAL": {
      "n": 4223,
      "hit_rate": 53.66,
      "avg_return_pct": 0.933,
      "median_return_pct": 0.494,
      "stdev_pct": 8.066,
      "profit_factor": 1.41,
      "best_pct": 55.155,
      "worst_pct": -35.018
    }
  },
  "option_proxy_aggregate": {
    "n": 8346,
    "hit_rate": 53.09,
    "avg_return_pct": 1.214,
    "median_return_pct": 0.563,
    "stdev_pct": 13.728,
    "profit_factor": 1.31,
    "best_pct": 104.423,
    "worst_pct": -76.172
  },
  "calibration": {
    "BULLISH": [
      {
        "min_score": 0.35,
        "max_score": 0.5,
        "n": 1086,
        "hit_rate": 56.63,
        "avg_return_pct": 1.356,
        "avg_option_proxy_return_pct": 1.85
      },
      {
        "min_score": 0.5,
        "max_score": 0.7,
        "n": 1740,
        "hit_rate": 55.52,
        "avg_return_pct": 0.954,
        "avg_option_proxy_return_pct": 1.371
      },
      {
        "min_score": 0.7,
        "max_score": 1.0,
        "n": 745,
        "hit_rate": 57.45,
        "avg_return_pct": 1.111,
        "avg_option_proxy_return_pct": 1.823
      }
    ],
    "BEARISH": [
      {
        "min_score": 0.5,
        "max_score": 0.7,
        "n": 293,
        "hit_rate": 52.9,
        "avg_return_pct": -0.167,
        "avg_option_proxy_return_pct": -0.635
      },
      {
        "min_score": 0.7,
        "max_score": 1.0,
        "n": 259,
        "hit_rate": 52.9,
        "avg_return_pct": -0.018,
        "avg_option_proxy_return_pct": -0.327
      }
    ],
    "NEUTRAL": [
      {
        "min_score": 0.0,
        "max_score": 0.2,
        "n": 1812,
        "hit_rate": 54.58,
        "avg_return_pct": 0.962,
        "avg_option_proxy_return_pct": 1.092
      },
      {
        "min_score": 0.2,
        "max_score": 0.35,
        "n": 1375,
        "hit_rate": 54.91,
        "avg_return_pct": 0.832,
        "avg_option_proxy_return_pct": 0.904
      },
      {
        "min_score": 0.35,
        "max_score": 0.5,
        "n": 630,
        "hit_rate": 51.43,
        "avg_return_pct": 0.64,
        "avg_option_proxy_return_pct": 0.7
      },
      {
        "min_score": 0.5,
        "max_score": 0.7,
        "n": 406,
        "hit_rate": 48.77,
        "avg_return_pct": 1.599,
        "avg_option_proxy_return_pct": 2.43
      }
    ]
  }
}